{
    "bonuses": [
        {
            "lighting": {
                "attenuationBegin": 50,
                "attenuationEnd": 500,
                "color": 16164153,
                "intensity": 0.5
            },
            "id": "nitro",
            "resourceId": 170010,
            "lifeTimeMs": 30000
        },
        {
            "lighting": {
                "attenuationBegin": 50,
                "attenuationEnd": 500,
                "color": 5889080,
                "intensity": 0.5
            },
            "id": "damage",
            "resourceId": 170011,
            "lifeTimeMs": 30000
        },
        {
            "lighting": {
                "attenuationBegin": 50,
                "attenuationEnd": 500,
                "color": 8972345,
                "intensity": 0.5
            },
            "id": "armor",
            "resourceId": 170006,
            "lifeTimeMs": 30000
        },
        {
            "lighting": {
                "attenuationBegin": 50,
                "attenuationEnd": 500,
                "color": 16220575,
                "intensity": 0.5
            },
            "id": "health",
            "resourceId": 170009,
            "lifeTimeMs": 30000
        },
        {
            "lighting": {
                "attenuationBegin": 50,
                "attenuationEnd": 500,
                "color": 3789046,
                "intensity": 0.5
            },
            "id": "crystall",
            "resourceId": 170007,
            "lifeTimeMs": 900000
        },
        {
            "lighting": {
                "attenuationBegin": 50,
                "attenuationEnd": 500,
                "color": 16175161,
                "intensity": 0.5
            },
            "id": "gold",
            "resourceId": 170008,
            "lifeTimeMs": 30000000
        },
        {
            "lighting": {
                "attenuationBegin": 50,
                "attenuationEnd": 500,
                "color": 16175161,
                "intensity": 0.5
            },
            "id": "special",
            "resourceId": 170012,
            "lifeTimeMs": 30000000
        },
        {
            "lighting": {
                "attenuationBegin": 100,
                "attenuationEnd": 500,
                "color": 15044128,
                "intensity": 1
            },
            "id": "moon",
            "resourceId": 170013,
            "lifeTimeMs": 30000000
        },
        {
            "lighting": {
                "attenuationBegin": 100,
                "attenuationEnd": 500,
                "color": 15044128,
                "intensity": 1
            },
            "id": "pumpkin",
            "resourceId": 170014,
            "lifeTimeMs": 30000000
        }
    ],
    "cordResource": 1000065,
    "parachuteInnerResource": 170005,
    "parachuteResource": 170004,
    "pickupSoundResource": 269321
}